<?xml version="1.0" encoding="UTF-8" ?>
<!DOCTYPE mapper PUBLIC "-//mybatis.org//DTD Mapper 3.0//EN" "http://mybatis.org/dtd/mybatis-3-mapper.dtd" >
<!-- 管理员持久化层XML配置继承IRoleDao -->
<mapper namespace="com.mingsoft.freight.dao.IFreightAreaDao">

	<!-- 将实体属性与表字段对接开始 -->
	<resultMap id="resultMap" type="com.mingsoft.freight.entity.FreightAreaEntity">
		<id column="fa_id" property="faId" />
		<result column="fa_title" property="faTitle" />
		<result column="fa_city_ids" property="faCityIds" />
	</resultMap>
	<!-- 将实体属性与表字段对接结束 -->
	<!-- 查询用户列表开始 -->
	<select id="queryAll" resultMap="resultMap">
		select * from freight_area
	</select>
	<!-- 查询用户列表结束 -->
	
	<!-- 新增用户开始 -->
	<insert id="saveEntity" useGeneratedKeys="true" keyProperty="peopleId"
		parameterType="com.mingsoft.base.entity.BaseEntity">
		
		insert into user(people_name,people_password,people_date_time) values (#{peopleName},#{peoplePassword},#{peopleDateTime})
		
	</insert>
	<!-- 新增用户结束 -->
	
	<!-- 更新用户开始 -->
	<update id="updateEntity" parameterType="com.mingsoft.base.entity.BaseEntity">
		update user set people_password = #{peoplePassword}	where people_name = #{peopleName}
		
	</update>
	<!-- 更新用户结束 -->
	<!-- 查询用户开始 -->
	<select id="getBYEntity" resultMap="resultMap" parameterType="int">
		select * from user 
		
		<where> 
			<if test=" peopleName != null ">and people_name= #{peopleName}</if>
			<if test=" peoplePassword != null ">and people_password= #{peoplePassword}</if>
		</where>
	</select>
	<!-- 查询用户结束 -->
	<!-- 删除用户开始 -->
	<delete id="areaDel" parameterType="int">
		delete from freight_area where fa_id = #{faId}
	</delete>
	<!-- 删除用户结束 -->
</mapper>